miscellaneous_slg/__init__.py
miscellaneous_slg-1.1.2.data/scripts/slg-domain-checker
miscellaneous_slg-1.1.2.data/scripts/slg-send-text-message
miscellaneous_slg-1.1.2.dist-info/METADATA
miscellaneous_slg-1.1.2.dist-info/WHEEL
miscellaneous_slg-1.1.2.dist-info/top_level.txt
miscellaneous_slg-1.1.2.dist-info/RECORD
