Metadata-Version: 2.1
Name: miscellaneous-slg
Version: 1.1.2
Summary: This is a description.
Requires-Python: >=3.6.3
Requires-Dist: aiosmtplib (==1.1.6)
